{
  "$schema": "https://ui.shadcn.com/schema/registry-item.json",
  "name": "theme",
  "type": "registry:theme",
  "title": "Nature Theme",
  "description": "A nature theme and styles with greens and browns using Tailwind and shadcn/ui variable names",
  "files": [
    {
      "path": "src/app/globals.css",
      "content": "@import \"tailwindcss\";\r\n@import \"tw-animate-css\";\r\n\r\n@custom-variant dark (&:is(.dark *));\r\n\r\n:root {\r\n  --background: oklch(0.97 0.01 80.72);\r\n  --foreground: oklch(0.3 0.04 30.2);\r\n\r\n  --card: oklch(0.97 0.01 80.72);\r\n  --card-foreground: oklch(0.3 0.04 30.2);\r\n\r\n  --popover: oklch(0.97 0.01 80.72);\r\n  --popover-foreground: oklch(0.3 0.04 30.2);\r\n\r\n  --primary: oklch(0.52 0.13 144.17);\r\n  --primary-foreground: oklch(1.0 0 0);\r\n\r\n  --secondary: oklch(0.96 0.02 147.64);\r\n  --secondary-foreground: oklch(0.43 0.12 144.31);\r\n\r\n  --muted: oklch(0.94 0.01 74.42);\r\n  --muted-foreground: oklch(0.45 0.05 39.21);\r\n\r\n  --accent: oklch(0.9 0.05 146.04);\r\n  --accent-foreground: oklch(0.43 0.12 144.31);\r\n\r\n  --destructive: oklch(0.54 0.19 26.72);\r\n  --destructive-foreground: oklch(1.0 0 0);\r\n\r\n  --border: oklch(0.88 0.02 74.64);\r\n  --input: oklch(0.88 0.02 74.64);\r\n  --ring: oklch(0.52 0.13 144.17);\r\n\r\n  --chart-1: oklch(0.67 0.16 144.21);\r\n  --chart-2: oklch(0.58 0.14 144.18);\r\n  --chart-3: oklch(0.52 0.13 144.17);\r\n  --chart-4: oklch(0.43 0.12 144.31);\r\n  --chart-5: oklch(0.22 0.05 145.73);\r\n\r\n  --sidebar: oklch(0.94 0.01 74.42);\r\n  --sidebar-foreground: oklch(0.3 0.04 30.2);\r\n  --sidebar-primary: oklch(0.52 0.13 144.17);\r\n  --sidebar-primary-foreground: oklch(1.0 0 0);\r\n  --sidebar-accent: oklch(0.9 0.05 146.04);\r\n  --sidebar-accent-foreground: oklch(0.43 0.12 144.31);\r\n  --sidebar-border: oklch(0.88 0.02 74.64);\r\n  --sidebar-ring: oklch(0.52 0.13 144.17);\r\n\r\n  --radius: 0.5rem;\r\n}\r\n\r\n.dark {\r\n  --background: oklch(0.15 0.01 74.42);\r\n  --foreground: oklch(0.95 0.02 80.72);\r\n\r\n  --card: oklch(0.12 0.01 80.72);\r\n  --card-foreground: oklch(0.95 0.02 80.72);\r\n\r\n  --popover: oklch(0.12 0.01 80.72);\r\n  --popover-foreground: oklch(0.95 0.02 80.72);\r\n\r\n  --primary: oklch(0.58 0.15 144.17);\r\n  --primary-foreground: oklch(0.09 0.01 80.72);\r\n\r\n  --secondary: oklch(0.15 0.02 147.64);\r\n  --secondary-foreground: oklch(0.65 0.12 144.31);\r\n\r\n  --muted: oklch(0.18 0.01 74.42);\r\n  --muted-foreground: oklch(0.65 0.03 74.42);\r\n\r\n  --accent: oklch(0.22 0.04 146.04);\r\n  --accent-foreground: oklch(0.65 0.12 144.31);\r\n\r\n  --destructive: oklch(0.62 0.22 26.72);\r\n  --destructive-foreground: oklch(0.95 0.02 80.72);\r\n\r\n  --border: oklch(0.22 0.02 74.64);\r\n  --input: oklch(0.22 0.02 74.64);\r\n  --ring: oklch(0.58 0.15 144.17);\r\n\r\n  --chart-1: oklch(0.72 0.16 144.21);\r\n  --chart-2: oklch(0.63 0.14 144.18);\r\n  --chart-3: oklch(0.58 0.15 144.17);\r\n  --chart-4: oklch(0.48 0.12 144.31);\r\n  --chart-5: oklch(0.35 0.08 145.73);\r\n\r\n  --sidebar: oklch(0.15 0.01 74.42);\r\n  --sidebar-foreground: oklch(0.95 0.02 80.72);\r\n  --sidebar-primary: oklch(0.58 0.15 144.17);\r\n  --sidebar-primary-foreground: oklch(0.09 0.01 80.72);\r\n  --sidebar-accent: oklch(0.22 0.04 146.04);\r\n  --sidebar-accent-foreground: oklch(0.65 0.12 144.31);\r\n  --sidebar-border: oklch(0.22 0.02 74.64);\r\n  --sidebar-ring: oklch(0.58 0.15 144.17);\r\n}\r\n\r\n@theme inline {\r\n  --color-background: var(--background);\r\n  --color-foreground: var(--foreground);\r\n\r\n  --color-primary: var(--primary);\r\n  --color-primary-foreground: var(--primary-foreground);\r\n\r\n  --color-secondary: var(--secondary);\r\n  --color-secondary-foreground: var(--secondary-foreground);\r\n  --color-accent: var(--accent);\r\n  --color-accent-foreground: var(--accent-foreground);\r\n\r\n  --color-muted: var(--muted);\r\n  --color-muted-foreground: var(--muted-foreground);\r\n  --color-card: var(--card);\r\n  --color-card-foreground: var(--card-foreground);\r\n  --color-popover: var(--popover);\r\n  --color-popover-foreground: var(--popover-foreground);\r\n\r\n  --color-border: var(--border);\r\n  --color-input: var(--input);\r\n  --color-ring: var(--ring);\r\n\r\n  --color-destructive: var(--destructive);\r\n  --color-destructive-foreground: var(--destructive-foreground);\r\n\r\n  --color-chart-1: var(--chart-1);\r\n  --color-chart-2: var(--chart-2);\r\n  --color-chart-3: var(--chart-3);\r\n  --color-chart-4: var(--chart-4);\r\n  --color-chart-5: var(--chart-5);\r\n\r\n  --color-sidebar: var(--sidebar);\r\n  --color-sidebar-foreground: var(--sidebar-foreground);\r\n  --color-sidebar-primary: var(--sidebar-primary);\r\n  --color-sidebar-primary-foreground: var(--sidebar-primary-foreground);\r\n  --color-sidebar-accent: var(--sidebar-accent);\r\n  --color-sidebar-accent-foreground: var(--sidebar-accent-foreground);\r\n  --color-sidebar-border: var(--sidebar-border);\r\n  --color-sidebar-ring: var(--sidebar-ring);\r\n\r\n  --font-sans: var(--font-sans);\r\n  --font-serif: var(--font-serif);\r\n  --font-mono: var(--font-mono);\r\n\r\n  --radius-sm: calc(var(--radius) - 4px);\r\n  --radius-md: calc(var(--radius) - 2px);\r\n  --radius-lg: var(--radius);\r\n  --radius-xl: calc(var(--radius) + 4px);\r\n\r\n  --shadow-2xs: var(--shadow-2xs);\r\n  --shadow-xs: var(--shadow-xs);\r\n  --shadow-sm: var(--shadow-sm);\r\n  --shadow: var(--shadow);\r\n  --shadow-md: var(--shadow-md);\r\n  --shadow-lg: var(--shadow-lg);\r\n  --shadow-xl: var(--shadow-xl);\r\n  --shadow-2xl: var(--shadow-2xl);\r\n}\r\n\r\n@layer base {\r\n  *,\r\n  ::after,\r\n  ::before,\r\n  ::backdrop,\r\n  ::file-selector-button {\r\n    border-color: var(--color-border, currentColor);\r\n  }\r\n}\r\n",
      "type": "registry:style",
      "target": "app/globals.css"
    },
    {
      "path": "postcss.config.mjs",
      "content": "/** @type {import('postcss-load-config').Config} */\r\nexport default {\r\n  plugins: {\r\n    \"@tailwindcss/postcss\": {},\r\n  },\r\n};\r\n",
      "type": "registry:file",
      "target": "postcss.config.mjs"
    }
  ],
  "cssVars": {
    "light": {
      "background": "oklch(0.97 0.01 80.72)",
      "foreground": "oklch(0.3 0.04 30.2)",
      "card": "oklch(0.97 0.01 80.72)",
      "card-foreground": "oklch(0.3 0.04 30.2)",
      "popover": "oklch(0.97 0.01 80.72)",
      "popover-foreground": "oklch(0.3 0.04 30.2)",
      "primary": "oklch(0.52 0.13 144.17)",
      "primary-foreground": "oklch(1.0 0 0)",
      "secondary": "oklch(0.96 0.02 147.64)",
      "secondary-foreground": "oklch(0.43 0.12 144.31)",
      "muted": "oklch(0.94 0.01 74.42)",
      "muted-foreground": "oklch(0.45 0.05 39.21)",
      "accent": "oklch(0.9 0.05 146.04)",
      "accent-foreground": "oklch(0.43 0.12 144.31)",
      "destructive": "oklch(0.54 0.19 26.72)",
      "destructive-foreground": "oklch(1.0 0 0)",
      "border": "oklch(0.88 0.02 74.64)",
      "input": "oklch(0.88 0.02 74.64)",
      "ring": "oklch(0.52 0.13 144.17)",
      "chart-1": "oklch(0.67 0.16 144.21)",
      "chart-2": "oklch(0.58 0.14 144.18)",
      "chart-3": "oklch(0.52 0.13 144.17)",
      "chart-4": "oklch(0.43 0.12 144.31)",
      "chart-5": "oklch(0.22 0.05 145.73)",
      "sidebar": "oklch(0.94 0.01 74.42)",
      "sidebar-foreground": "oklch(0.3 0.04 30.2)",
      "sidebar-primary": "oklch(0.52 0.13 144.17)",
      "sidebar-primary-foreground": "oklch(1.0 0 0)",
      "sidebar-accent": "oklch(0.9 0.05 146.04)",
      "sidebar-accent-foreground": "oklch(0.43 0.12 144.31)",
      "sidebar-border": "oklch(0.88 0.02 74.64)",
      "sidebar-ring": "oklch(0.52 0.13 144.17)",
      "radius": "0.5rem"
    },
    "dark": {
      "background": "oklch(0.15 0.01 74.42)",
      "foreground": "oklch(0.95 0.02 80.72)",
      "card": "oklch(0.12 0.01 80.72)",
      "card-foreground": "oklch(0.95 0.02 80.72)",
      "popover": "oklch(0.12 0.01 80.72)",
      "popover-foreground": "oklch(0.95 0.02 80.72)",
      "primary": "oklch(0.58 0.15 144.17)",
      "primary-foreground": "oklch(0.09 0.01 80.72)",
      "secondary": "oklch(0.15 0.02 147.64)",
      "secondary-foreground": "oklch(0.65 0.12 144.31)",
      "muted": "oklch(0.18 0.01 74.42)",
      "muted-foreground": "oklch(0.65 0.03 74.42)",
      "accent": "oklch(0.22 0.04 146.04)",
      "accent-foreground": "oklch(0.65 0.12 144.31)",
      "destructive": "oklch(0.62 0.22 26.72)",
      "destructive-foreground": "oklch(0.95 0.02 80.72)",
      "border": "oklch(0.22 0.02 74.64)",
      "input": "oklch(0.22 0.02 74.64)",
      "ring": "oklch(0.58 0.15 144.17)",
      "chart-1": "oklch(0.72 0.16 144.21)",
      "chart-2": "oklch(0.63 0.14 144.18)",
      "chart-3": "oklch(0.58 0.15 144.17)",
      "chart-4": "oklch(0.48 0.12 144.31)",
      "chart-5": "oklch(0.35 0.08 145.73)",
      "sidebar": "oklch(0.15 0.01 74.42)",
      "sidebar-foreground": "oklch(0.95 0.02 80.72)",
      "sidebar-primary": "oklch(0.58 0.15 144.17)",
      "sidebar-primary-foreground": "oklch(0.09 0.01 80.72)",
      "sidebar-accent": "oklch(0.22 0.04 146.04)",
      "sidebar-accent-foreground": "oklch(0.65 0.12 144.31)",
      "sidebar-border": "oklch(0.22 0.02 74.64)",
      "sidebar-ring": "oklch(0.58 0.15 144.17)",
      "radius": "0.5rem"
    }
  }
}